config.py
converters.py
memory.py
memory_commands.py
migrate.py
parsers.py
utils.py
validation.py
rule_migration_agent-1.1.0.dist-info/METADATA
rule_migration_agent-1.1.0.dist-info/WHEEL
rule_migration_agent-1.1.0.dist-info/entry_points.txt
rule_migration_agent-1.1.0.dist-info/top_level.txt
rule_migration_agent-1.1.0.dist-info/RECORD
