Metadata-Version: 2.1
Name: rule-migration-agent
Version: 1.1.0
Summary: Bidirectional conversion tool for migrating between Cursor rules and Claude Skills
Home-page: https://github.com/patrikmichi/rule-migration-agent
Author: patrikmichi
Author-email: 
License: MIT
Project-URL: Homepage, https://github.com/patrikmichi/rule-migration-agent
Project-URL: Documentation, https://github.com/patrikmichi/rule-migration-agent#readme
Project-URL: Repository, https://github.com/patrikmichi/rule-migration-agent
Project-URL: Bug Tracker, https://github.com/patrikmichi/rule-migration-agent/issues
Keywords: cursor,claude,rules,skills,migration,conversion,ai,agent
Classifier: Development Status :: 4 - Beta
Classifier: Intended Audience :: Developers
Classifier: License :: OSI Approved :: MIT License
Classifier: Programming Language :: Python :: 3
Classifier: Programming Language :: Python :: 3.8
Classifier: Programming Language :: Python :: 3.9
Classifier: Programming Language :: Python :: 3.10
Classifier: Programming Language :: Python :: 3.11
Classifier: Programming Language :: Python :: 3.12
Classifier: Topic :: Software Development :: Libraries :: Python Modules
Classifier: Topic :: Software Development :: Version Control
Classifier: Topic :: Text Processing :: Markup
Requires-Python: >=3.8
Requires-Dist: PyYAML>=6.0
Requires-Dist: requests>=2.31.0
Requires-Dist: beautifulsoup4>=4.12.0
Requires-Dist: tqdm>=4.66.0
Requires-Dist: rich>=13.7.0
Provides-Extra: dev
Requires-Dist: pytest>=7.0; extra == "dev"
Requires-Dist: pytest-cov>=4.0; extra == "dev"
Requires-Dist: black>=23.0; extra == "dev"
Requires-Dist: flake8>=6.0; extra == "dev"
